pylusat/__init__.py
pylusat/_version.py
pylusat/base.py
pylusat/density.py
pylusat/distance.py
pylusat/geotools.py
pylusat/interpolate.py
pylusat/rescale.py
pylusat/utils.py
pylusat/zonal.py
pylusat/datasets/__init__.py
pylusat/datasets/acs2016/acs2016.CPG
pylusat/datasets/acs2016/acs2016.dbf
pylusat/datasets/acs2016/acs2016.prj
pylusat/datasets/acs2016/acs2016.sbn
pylusat/datasets/acs2016/acs2016.sbx
pylusat/datasets/acs2016/acs2016.shp
pylusat/datasets/acs2016/acs2016.shp.xml
pylusat/datasets/acs2016/acs2016.shx
pylusat/datasets/habitat/habitat.tfw
pylusat/datasets/habitat/habitat.tif
pylusat/datasets/habitat/habitat.tif.aux.xml
pylusat/datasets/habitat/habitat.tif.ovr
pylusat/datasets/habitat/habitat.tif.vat.cpg
pylusat/datasets/habitat/habitat.tif.vat.dbf
pylusat/datasets/habitat_fl_stateplane/habitat_fl_stateplane.tfw
pylusat/datasets/habitat_fl_stateplane/habitat_fl_stateplane.tif
pylusat/datasets/habitat_fl_stateplane/habitat_fl_stateplane.tif.aux.xml
pylusat/datasets/habitat_fl_stateplane/habitat_fl_stateplane.tif.ovr
pylusat/datasets/habitat_fl_stateplane/habitat_fl_stateplane.tif.vat.cpg
pylusat/datasets/habitat_fl_stateplane/habitat_fl_stateplane.tif.vat.dbf
pylusat/datasets/habitat_fl_stateplane/habitat_fl_stateplane.tif.xml
pylusat/datasets/habitat_shift/habitat_shift.tfw
pylusat/datasets/habitat_shift/habitat_shift.tif
pylusat/datasets/habitat_shift/habitat_shift.tif.aux.xml
pylusat/datasets/habitat_shift/habitat_shift.tif.ovr
pylusat/datasets/habitat_shift/habitat_shift.tif.vat.cpg
pylusat/datasets/habitat_shift/habitat_shift.tif.vat.dbf
pylusat/datasets/habitat_shift/habitat_shift.tif.xml
pylusat/datasets/highway/highway.cpg
pylusat/datasets/highway/highway.dbf
pylusat/datasets/highway/highway.prj
pylusat/datasets/highway/highway.sbn
pylusat/datasets/highway/highway.sbx
pylusat/datasets/highway/highway.shp
pylusat/datasets/highway/highway.shp.xml
pylusat/datasets/highway/highway.shx
pylusat/datasets/schools/schools.CPG
pylusat-0.5.8.dist-info/LICENSE.txt
pylusat-0.5.8.dist-info/METADATA
pylusat-0.5.8.dist-info/WHEEL
pylusat-0.5.8.dist-info/top_level.txt
pylusat-0.5.8.dist-info/RECORD
